README.md
setup.cfg
setup.py
sehavniva/__init__.py
sehavniva/const.py
sehavniva/main.py
sehavniva/sehavniva.py
sehavniva.egg-info/PKG-INFO
sehavniva.egg-info/SOURCES.txt
sehavniva.egg-info/dependency_links.txt
sehavniva.egg-info/requires.txt
sehavniva.egg-info/top_level.txt